{
    "backend": "flask",
    "db_name": "",
    "db_pass": "",
    "db_type": "mysql",
    "db_user": "",
    "dbms": "1",
    "description": "generated product",
    "design": "soft-ui-dashboard",
    "docker": "0",
    "err_code": 0,
    "frontend": "",
    "heroku": "0",
    "pattern": "mvc",
    "pro": "0",
    "task_id": "efe66654-ff65-41d2-812a-334b2c671089",
    "task_info": "Upload Sources [0%] - 330 files",
    "task_output": "efe66654-ff65-41d2-812a-334b2c671089.zip",
    "task_result": "SUCCESS",
    "task_state": "RUNNING",
    "task_ts_end": "2023-02-19-07-54-06",
    "task_ts_start": "2023-02-19-07-54-03"
}